engelliler_sarayi/__init__.py
engelliler_sarayi/gorunurluk.py
engelliler_sarayi/okunabilirlik.py
engelliler_sarayi/seslendirme.py
engelliler_sarayi-0.2.0.dist-info/licenses/LICENSE
engelliler_sarayi-0.2.0.dist-info/METADATA
engelliler_sarayi-0.2.0.dist-info/WHEEL
engelliler_sarayi-0.2.0.dist-info/top_level.txt
engelliler_sarayi-0.2.0.dist-info/RECORD
