Metadata-Version: 2.4
Name: engelliler-sarayi
Version: 0.2.0
Summary: Görsel, işitsel ve bilişsel erişilebilirlik için Python araçları.
Home-page: https://github.com/kullanici-adiniz/engelliler-sarayi-projesi
Author: Miraç Birben
Author-email: miracbirben@gmail.com
Classifier: Programming Language :: Python :: 3
Classifier: License :: OSI Approved :: MIT License
Classifier: Operating System :: OS Independent
Classifier: Intended Audience :: Developers
Classifier: Topic :: Software Development :: Libraries :: Python Modules
Classifier: Topic :: Utilities
Classifier: Topic :: Text Processing
Requires-Python: >=3.6
License-File: LICENSE
Requires-Dist: pyttsx3
Dynamic: author
Dynamic: author-email
Dynamic: classifier
Dynamic: description
Dynamic: description-content-type
Dynamic: home-page
Dynamic: license-file
Dynamic: requires-dist
Dynamic: requires-python
Dynamic: summary
